register_printer/VERSION
register_printer/__init__.py
register_printer/__main__.py
register_printer/get_version.py
register_printer/register_printer.py
register_printer/template_loader.py
register_printer/constants/__init__.py
register_printer/data_model/__init__.py
register_printer/data_model/array.py
register_printer/data_model/array_template.py
register_printer/data_model/block.py
register_printer/data_model/block_instance.py
register_printer/data_model/block_template.py
register_printer/data_model/field.py
register_printer/data_model/field_template.py
register_printer/data_model/register.py
register_printer/data_model/register_template.py
register_printer/data_model/struct.py
register_printer/data_model/top_sys.py
register_printer/data_model/utility.py
register_printer/generators/__init__.py
register_printer/generators/c_header_generator/__init__.py
register_printer/generators/c_header_generator/c_header_generator.py
register_printer/generators/c_header_generator/print_c_header.py
register_printer/generators/c_header_generator/print_c_header_block.py
register_printer/generators/c_header_generator/print_c_header_sys.py
register_printer/generators/c_header_generator/print_c_test.py
register_printer/generators/doc_generator/__init__.py
register_printer/generators/doc_generator/doc_generator.py
register_printer/generators/doc_generator/print_doc.py
register_printer/generators/excel_generator/__init__.py
register_printer/generators/excel_generator/excel_generator.py
register_printer/generators/rtl_generator/__init__.py
register_printer/generators/rtl_generator/print_rtl.py
register_printer/generators/rtl_generator/rtl_generator.py
register_printer/generators/uvm_generator/__init__.py
register_printer/generators/uvm_generator/print_sv_defines.py
register_printer/generators/uvm_generator/print_uvm.py
register_printer/generators/uvm_generator/print_uvm_block.py
register_printer/generators/uvm_generator/print_uvm_sys.py
register_printer-1.1.21.dist-info/LICENSE
register_printer-1.1.21.dist-info/METADATA
register_printer-1.1.21.dist-info/WHEEL
register_printer-1.1.21.dist-info/entry_points.txt
register_printer-1.1.21.dist-info/top_level.txt
register_printer-1.1.21.dist-info/RECORD
