Metadata-Version: 2.1
Name: register-printer
Version: 1.1.21
Summary: A tool to generate register codes.
Home-page: https://github.com/zhangyiant/RegisterPrinter.git
Author: Yi Zhang
Author-email: zhangyiant@hotmail.com
Classifier: Programming Language :: Python :: 3
Classifier: License :: OSI Approved :: MIT License
Classifier: Operating System :: OS Independent
Requires-Python: >=3.7
License-File: LICENSE
Requires-Dist: Jinja2 (>=2.11)
Requires-Dist: openpyxl (>=3.0)
Requires-Dist: python-docx (>=0.8)
Requires-Dist: xlrd (<=1.2)
